Metadata-Version: 1.1
Name: minidoc
Version: 0.0.4
Summary: auto generate a mini rst doc (code block + svg) from a test-file
Home-page: https://github.com/ihgazni2/minidoc
Author: dli
Author-email: 286264978@qq.com
License: MIT license
Keywords: doc,test,svg
Platform: UNKNOWN
Classifier: Environment :: Console
Classifier: Environment :: Web Environment
Classifier: Intended Audience :: End Users/Desktop
Classifier: Intended Audience :: Developers
Classifier: Intended Audience :: System Administrators
Classifier: Programming Language :: Python :: 3
Classifier: Programming Language :: Python :: 3.3
Classifier: Programming Language :: Python :: 3.4
Classifier: Programming Language :: Python :: 3.5
Classifier: Programming Language :: Python :: 3.6
Classifier: Programming Language :: Python :: 3.7
